{
  "player": {
    "name": "Riven Ashguard",
    "race": "Half-Orc",
    "class_name": "Fighter",
    "background": "Soldier",
    "level": 4,
    "ability_scores": {
      "STR": 17,
      "DEX": 12,
      "CON": 15,
      "INT": 8,
      "WIS": 10,
      "CHA": 13
    },
    "skill_proficiencies": [
      "Acrobatics",
      "Athletics",
      "History",
      "Insight",
      "Intimidation",
      "Perception",
      "Survival"
    ],
    "saving_throw_proficiencies": [
      "STR",
      "CON"
    ],
    "features": [
      "action_surge",
      "improved_critical",
      "martial_mastery",
      "menacing",
      "relentless_endurance",
      "second_wind"
    ],
    "weapon": {
      "name": "Roadworn Longsword",
      "damage": "1d8",
      "ability": "STR",
      "weapon_type": "longsword",
      "to_hit_bonus": 0,
      "damage_bonus": 0,
      "finesse": false,
      "ranged": false,
      "hands_required": 1,
      "properties": [
        "versatile"
      ]
    },
    "armor": {
      "name": "Roadworn Chain Mail",
      "base_ac": 16,
      "armor_type": "heavy",
      "dex_cap": 0,
      "heavy": true,
      "stealth_disadvantage": true
    },
    "hit_die": 10,
    "current_hp": 36,
    "max_hp": 36,
    "shield": true,
    "spellcasting_ability": null,
    "skill_expertise": [],
    "bonus_proficiencies": [
      "Land Vehicles",
      "Gaming Set"
    ],
    "resources": {
      "second_wind": 1,
      "action_surge": 1
    },
    "max_resources": {
      "second_wind": 1,
      "action_surge": 1
    },
    "inventory": {},
    "conditions": {
      "emboldened": 2
    },
    "equipment_bonuses": {
      "Athletics": 1,
      "Intimidation": 1,
      "attack": 1,
      "damage": 1
    },
    "gear_bonuses": {
      "AC": 0
    },
    "notes": [
      "Veteran's kit: +1 to Athletics and Intimidation checks.",
      "A brutal shield-line veteran built to absorb pressure and keep swinging in the thick of a fight.",
      "Preset build: optimized for faster testing and quick starts."
    ],
    "tags": [
      "hero"
    ],
    "equipment_slots": {
      "head": null,
      "ring_1": null,
      "ring_2": null,
      "neck": null,
      "chest": "chain_mail_common",
      "gloves": null,
      "boots": null,
      "main_hand": "longsword_common",
      "off_hand": "shield_common",
      "cape": null
    },
    "archetype": "fighter",
    "companion_id": "",
    "disposition": 0,
    "lore": [],
    "bond_flags": {},
    "relationship_bonuses": {},
    "stable": false,
    "dead": false,
    "death_successes": 0,
    "death_failures": 0,
    "temp_hp": 0,
    "xp_value": 0,
    "gold_value": 0
  },
  "companions": [
    {
      "name": "Bryn Underbough",
      "race": "Halfling",
      "class_name": "Rogue",
      "background": "Criminal",
      "level": 4,
      "ability_scores": {
        "STR": 8,
        "DEX": 17,
        "CON": 12,
        "INT": 13,
        "WIS": 14,
        "CHA": 10
      },
      "skill_proficiencies": [
        "Acrobatics",
        "Athletics",
        "Deception",
        "Insight",
        "Intimidation",
        "Perception",
        "Persuasion",
        "Sleight of Hand",
        "Stealth"
      ],
      "saving_throw_proficiencies": [
        "DEX",
        "INT"
      ],
      "features": [
        "brave",
        "cunning_action",
        "evasion",
        "expertise",
        "improved_sneak_attack",
        "lucky",
        "sneak_attack"
      ],
      "weapon": {
        "name": "Roadworn Shortsword",
        "damage": "1d6",
        "ability": "FINESSE",
        "weapon_type": "shortsword",
        "to_hit_bonus": 0,
        "damage_bonus": 0,
        "finesse": true,
        "ranged": false,
        "hands_required": 1,
        "properties": [
          "finesse",
          "light"
        ]
      },
      "armor": {
        "name": "Roadworn Leather Armor",
        "base_ac": 11,
        "armor_type": "light",
        "dex_cap": null,
        "heavy": false,
        "stealth_disadvantage": false
      },
      "hit_die": 8,
      "current_hp": 27,
      "max_hp": 27,
      "shield": false,
      "spellcasting_ability": null,
      "skill_expertise": [
        "Perception",
        "Stealth"
      ],
      "bonus_proficiencies": [
        "Thieves' Tools",
        "Disguise Kit"
      ],
      "resources": {},
      "max_resources": {},
      "inventory": {},
      "conditions": {},
      "equipment_bonuses": {
        "Stealth": 3,
        "Sleight of Hand": 1,
        "initiative": 2,
        "DEX_save": 2
      },
      "gear_bonuses": {},
      "notes": [
        "Thieves' tools: +1 to Stealth and Sleight of Hand checks.",
        "A caravan scout who knows every shortcut between Phandalin and Neverwinter.",
        "A halfling scout who hides anxiety behind wit, speed, and relentless observation."
      ],
      "tags": [
        "hero",
        "companion"
      ],
      "equipment_slots": {
        "head": null,
        "ring_1": null,
        "ring_2": null,
        "neck": null,
        "chest": "leather_armor_common",
        "gloves": null,
        "boots": null,
        "main_hand": "shortsword_common",
        "off_hand": null,
        "cape": null
      },
      "archetype": "rogue",
      "companion_id": "bryn_underbough",
      "disposition": 0,
      "lore": [
        "Bryn grew up between caravans, shrines, and borrowed rooms, learning early that knowing an exit mattered as much as knowing a friend.",
        "She ran messages for smugglers in her teens before deciding she preferred honest pay and fewer knives at her back.",
        "Her humor gets sharper whenever she is frightened enough to think someone might notice."
      ],
      "bond_flags": {
        "talked_topics": []
      },
      "relationship_bonuses": {},
      "stable": false,
      "dead": false,
      "death_successes": 0,
      "death_failures": 0,
      "temp_hp": 0,
      "xp_value": 0,
      "gold_value": 0
    },
    {
      "name": "Elira Dawnmantle",
      "race": "Human",
      "class_name": "Cleric",
      "background": "Acolyte",
      "level": 4,
      "ability_scores": {
        "STR": 11,
        "DEX": 13,
        "CON": 14,
        "INT": 11,
        "WIS": 16,
        "CHA": 15
      },
      "skill_proficiencies": [
        "History",
        "Insight",
        "Medicine",
        "Persuasion",
        "Religion"
      ],
      "saving_throw_proficiencies": [
        "WIS",
        "CHA"
      ],
      "features": [
        "channel_divinity",
        "cleric_spellcasting",
        "disciple_of_life",
        "radiant_potency"
      ],
      "weapon": {
        "name": "Roadworn Mace",
        "damage": "1d6",
        "ability": "STR",
        "weapon_type": "mace",
        "to_hit_bonus": 0,
        "damage_bonus": 0,
        "finesse": false,
        "ranged": false,
        "hands_required": 1,
        "properties": []
      },
      "armor": {
        "name": "Roadworn Scale Mail",
        "base_ac": 14,
        "armor_type": "medium",
        "dex_cap": 2,
        "heavy": false,
        "stealth_disadvantage": true
      },
      "hit_die": 8,
      "current_hp": 31,
      "max_hp": 31,
      "shield": true,
      "spellcasting_ability": "WIS",
      "skill_expertise": [],
      "bonus_proficiencies": [
        "Calligrapher's Supplies",
        "Celestial"
      ],
      "resources": {
        "spell_slots_1": 4,
        "channel_divinity": 1,
        "spell_slots_2": 3
      },
      "max_resources": {
        "spell_slots_1": 4,
        "channel_divinity": 1,
        "spell_slots_2": 3
      },
      "inventory": {},
      "conditions": {},
      "equipment_bonuses": {
        "Medicine": 1,
        "Religion": 1,
        "healing": 2,
        "spell_damage": 1
      },
      "gear_bonuses": {
        "AC": 0
      },
      "notes": [
        "Healer's satchel: +1 to Medicine and Religion checks.",
        "A priestess of Tymora tending the frontier faithful in Phandalin.",
        "A priestess of Tymora whose compassion is sharpened, not softened, by the frontier's cruelty."
      ],
      "tags": [
        "hero",
        "companion"
      ],
      "equipment_slots": {
        "head": null,
        "ring_1": null,
        "ring_2": null,
        "neck": null,
        "chest": "scale_mail_common",
        "gloves": null,
        "boots": null,
        "main_hand": "mace_common",
        "off_hand": "shield_common",
        "cape": null
      },
      "archetype": "cleric",
      "companion_id": "elira_dawnmantle",
      "disposition": 0,
      "lore": [
        "Elira learned battlefield triage from roadside shrines that treated lumber crews, miners, and pilgrims with equal urgency.",
        "She believes luck is not random mercy but a chance people build for one another with courage and timing.",
        "Under stress she gets quieter, not colder, as though she is measuring every word for whether it heals or harms."
      ],
      "bond_flags": {
        "talked_topics": []
      },
      "relationship_bonuses": {},
      "stable": false,
      "dead": false,
      "death_successes": 0,
      "death_failures": 0,
      "temp_hp": 0,
      "xp_value": 0,
      "gold_value": 0
    },
    {
      "name": "Tolan Ironshield",
      "race": "Dwarf",
      "class_name": "Fighter",
      "background": "Soldier",
      "level": 4,
      "ability_scores": {
        "STR": 15,
        "DEX": 10,
        "CON": 16,
        "INT": 8,
        "WIS": 12,
        "CHA": 13
      },
      "skill_proficiencies": [
        "Animal Handling",
        "Athletics",
        "History",
        "Insight",
        "Intimidation",
        "Perception",
        "Survival"
      ],
      "saving_throw_proficiencies": [
        "STR",
        "CON"
      ],
      "features": [
        "action_surge",
        "darkvision",
        "dwarven_resilience",
        "improved_critical",
        "martial_mastery",
        "second_wind"
      ],
      "weapon": {
        "name": "Roadworn Longsword",
        "damage": "1d8",
        "ability": "STR",
        "weapon_type": "longsword",
        "to_hit_bonus": 0,
        "damage_bonus": 0,
        "finesse": false,
        "ranged": false,
        "hands_required": 1,
        "properties": [
          "versatile"
        ]
      },
      "armor": {
        "name": "Roadworn Chain Mail",
        "base_ac": 16,
        "armor_type": "heavy",
        "dex_cap": 0,
        "heavy": true,
        "stealth_disadvantage": true
      },
      "hit_die": 10,
      "current_hp": 40,
      "max_hp": 40,
      "shield": true,
      "spellcasting_ability": null,
      "skill_expertise": [],
      "bonus_proficiencies": [
        "Land Vehicles",
        "Gaming Set"
      ],
      "resources": {
        "second_wind": 1,
        "action_surge": 1
      },
      "max_resources": {
        "second_wind": 1,
        "action_surge": 1
      },
      "inventory": {},
      "conditions": {},
      "equipment_bonuses": {
        "Athletics": 1,
        "Intimidation": 1,
        "attack": 1,
        "damage": 1
      },
      "gear_bonuses": {
        "AC": 0
      },
      "notes": [
        "Veteran's kit: +1 to Athletics and Intimidation checks.",
        "A caravan guard from Neverwinter with a shield wall mindset.",
        "A dwarven shield veteran who measures people by whether they hold the line when it matters."
      ],
      "tags": [
        "hero",
        "companion"
      ],
      "equipment_slots": {
        "head": null,
        "ring_1": null,
        "ring_2": null,
        "neck": null,
        "chest": "chain_mail_common",
        "gloves": null,
        "boots": null,
        "main_hand": "longsword_common",
        "off_hand": "shield_common",
        "cape": null
      },
      "archetype": "fighter",
      "companion_id": "tolan_ironshield",
      "disposition": 0,
      "lore": [
        "Tolan served on caravan routes out of Neverwinter for two decades, long enough to see three trade leagues fail and two rise in their place.",
        "He still carries a notched tower-shield rivet from the ambush that killed his older brother near the Mere of Dead Men.",
        "He trusts steady action more than speeches, but remembers every promise anyone makes in his hearing."
      ],
      "bond_flags": {
        "talked_topics": []
      },
      "relationship_bonuses": {},
      "stable": false,
      "dead": false,
      "death_successes": 0,
      "death_failures": 0,
      "temp_hp": 0,
      "xp_value": 0,
      "gold_value": 0
    }
  ],
  "camp_companions": [],
  "current_act": 2,
  "current_scene": "act2_claims_council",
  "flags": {
    "act1_started": true,
    "briefing_seen": true,
    "phandalin_council_seen": true,
    "steward_vow_made": true,
    "miners_exchange_dispute_resolved": true,
    "miners_exchange_ledgers_checked": true,
    "elira_helped": true,
    "dev_god_mode": false,
    "dev_pass_every_dice_check": false,
    "introduced_characters": [
      "Ashen Brand Runner",
      "Bryn Underbough",
      "Elira Dawnmantle",
      "Tolan Ironshield"
    ],
    "map_state": {
      "current_node_id": "neverwinter_briefing",
      "current_dungeon_id": null,
      "current_room_id": null,
      "visited_nodes": [],
      "cleared_rooms": [],
      "seen_story_beats": [
        "stonehill_council"
      ],
      "node_history": [],
      "room_history": []
    },
    "act2_started": true,
    "act2_scaffold_enabled": true,
    "act2_town_stability": 5,
    "act2_route_control": 5,
    "act2_whisper_pressure": 0,
    "act2_sponsor": "council",
    "act2_captive_outcome": "uncertain",
    "act2_metrics_initialized": true
  },
  "clues": [],
  "journal": [
    "You broke the Ashen Brand and secured Phandalin through the end of Act 1.",
    "Bryn Underbough joined the active party.",
    "Elira Dawnmantle joined the active party.",
    "Tolan Ironshield joined the active party.",
    "Act 2 begins with a claims war around Wave Echo Cave, a town trying to stay intact, and a cult using the mine's old song as a listening tool.",
    "Reward from South Barracks Breakout: 50 XP, 8 gp."
  ],
  "quests": {},
  "completed_acts": [
    1
  ],
  "xp": 2750,
  "gold": 28,
  "inventory": {
    "potion_healing": 5,
    "bread_round": 4,
    "travel_biscuits": 4,
    "dried_fish": 3,
    "goat_cheese": 2,
    "frontier_ale": 2,
    "root_vegetables": 2,
    "antitoxin_vial": 1,
    "chain_mail_common": 2,
    "longsword_common": 2,
    "shield_common": 3,
    "leather_armor_common": 1,
    "shortsword_common": 1,
    "scale_mail_common": 1,
    "mace_common": 1
  },
  "short_rests_remaining": 2
}