{
  "player": {
    "name": "Riven Ashguard",
    "race": "Half-Orc",
    "class_name": "Fighter",
    "background": "Soldier",
    "level": 1,
    "ability_scores": {
      "STR": 17,
      "DEX": 12,
      "CON": 15,
      "INT": 8,
      "WIS": 10,
      "CHA": 13
    },
    "skill_proficiencies": [
      "Athletics",
      "Intimidation",
      "Perception",
      "Survival"
    ],
    "saving_throw_proficiencies": [
      "STR",
      "CON"
    ],
    "features": [
      "menacing",
      "relentless_endurance",
      "second_wind"
    ],
    "weapon": {
      "name": "Roadworn Longsword",
      "damage": "1d8",
      "ability": "STR",
      "weapon_type": "longsword",
      "to_hit_bonus": 0,
      "damage_bonus": 0,
      "finesse": false,
      "ranged": false,
      "hands_required": 1,
      "properties": [
        "versatile"
      ]
    },
    "armor": {
      "name": "Roadworn Chain Mail",
      "base_ac": 16,
      "armor_type": "heavy",
      "dex_cap": 0,
      "heavy": true,
      "stealth_disadvantage": true
    },
    "hit_die": 10,
    "current_hp": 12,
    "max_hp": 12,
    "shield": true,
    "spellcasting_ability": null,
    "skill_expertise": [],
    "bonus_proficiencies": [
      "Land Vehicles",
      "Gaming Set"
    ],
    "resources": {
      "second_wind": 1
    },
    "max_resources": {
      "second_wind": 1
    },
    "inventory": {},
    "conditions": {},
    "equipment_bonuses": {
      "Athletics": 1,
      "Intimidation": 1
    },
    "gear_bonuses": {
      "AC": 0
    },
    "notes": [
      "Veteran's kit: +1 to Athletics and Intimidation checks.",
      "A brutal shield-line veteran built to absorb pressure and keep swinging in the thick of a fight.",
      "Preset build: optimized for faster testing and quick starts."
    ],
    "tags": [
      "hero"
    ],
    "equipment_slots": {
      "head": null,
      "ring_1": null,
      "ring_2": null,
      "neck": null,
      "chest": "chain_mail_common",
      "gloves": null,
      "boots": null,
      "main_hand": "longsword_common",
      "off_hand": "shield_common",
      "cape": null
    },
    "archetype": "fighter",
    "companion_id": "",
    "disposition": 0,
    "lore": [],
    "bond_flags": {},
    "relationship_bonuses": {},
    "stable": false,
    "dead": false,
    "death_successes": 0,
    "death_failures": 0,
    "temp_hp": 0,
    "xp_value": 0,
    "gold_value": 0
  },
  "companions": [
    {
      "name": "Rhogar Valeguard",
      "race": "Dragonborn",
      "class_name": "Paladin",
      "background": "Soldier",
      "level": 1,
      "ability_scores": {
        "STR": 17,
        "DEX": 10,
        "CON": 13,
        "INT": 8,
        "WIS": 12,
        "CHA": 15
      },
      "skill_proficiencies": [
        "Athletics",
        "Intimidation",
        "Persuasion"
      ],
      "saving_throw_proficiencies": [
        "WIS",
        "CHA"
      ],
      "features": [
        "divine_smite",
        "draconic_presence",
        "lay_on_hands"
      ],
      "weapon": {
        "name": "Roadworn Longsword",
        "damage": "1d8",
        "ability": "STR",
        "weapon_type": "longsword",
        "to_hit_bonus": 0,
        "damage_bonus": 0,
        "finesse": false,
        "ranged": false,
        "hands_required": 1,
        "properties": [
          "versatile"
        ]
      },
      "armor": {
        "name": "Roadworn Chain Mail",
        "base_ac": 16,
        "armor_type": "heavy",
        "dex_cap": 0,
        "heavy": true,
        "stealth_disadvantage": true
      },
      "hit_die": 10,
      "current_hp": 6,
      "max_hp": 11,
      "shield": true,
      "spellcasting_ability": "CHA",
      "skill_expertise": [],
      "bonus_proficiencies": [
        "Land Vehicles",
        "Gaming Set"
      ],
      "resources": {
        "lay_on_hands": 5
      },
      "max_resources": {
        "lay_on_hands": 5
      },
      "inventory": {},
      "conditions": {},
      "equipment_bonuses": {
        "Athletics": 1,
        "Intimidation": 1
      },
      "gear_bonuses": {
        "AC": 0
      },
      "notes": [
        "Veteran's kit: +1 to Athletics and Intimidation checks.",
        "A dragonborn sworn to protect caravans on the road south of Greywake.",
        "A dragonborn oathsworn who treats duty like a living thing that must be fed by action."
      ],
      "tags": [
        "hero",
        "companion"
      ],
      "equipment_slots": {
        "head": null,
        "ring_1": null,
        "ring_2": null,
        "neck": null,
        "chest": "chain_mail_common",
        "gloves": null,
        "boots": null,
        "main_hand": "longsword_common",
        "off_hand": "shield_common",
        "cape": null
      },
      "archetype": "paladin",
      "companion_id": "rhogar_valeguard",
      "disposition": 0,
      "lore": [
        "Rhogar was raised among caravan wardens who believed a sworn road was as sacred as any temple threshold.",
        "He carries every oath like a visible weight and grows restless whenever words are left unfinished.",
        "His confidence comes easily, but his forgiveness does not; once broken, his trust has to be rebuilt with deeds."
      ],
      "bond_flags": {
        "talked_topics": []
      },
      "relationship_bonuses": {},
      "stable": false,
      "dead": false,
      "death_successes": 0,
      "death_failures": 0,
      "temp_hp": 0,
      "xp_value": 0,
      "gold_value": 0
    }
  ],
  "camp_companions": [],
  "current_act": 1,
  "current_scene": "blackwake_crossing",
  "flags": {
    "act1_started": true,
    "map_state": {
      "current_node_id": "blackwake_crossing",
      "current_dungeon_id": "blackwake_crossing_branch",
      "current_room_id": "charred_tollhouse",
      "visited_nodes": [
        "greywake_briefing",
        "emberway_ambush",
        "iron_hollow_hub"
      ],
      "cleared_rooms": [
        "charred_tollhouse"
      ],
      "seen_story_beats": [],
      "room_history": []
    },
    "introduced_characters": [
      "Ashen Brand Runner",
      "Mira Thann",
      "Rhogar Valeguard"
    ],
    "background_prologue_completed": "Soldier",
    "briefing_seen": true,
    "briefing_q_greywake": true,
    "briefing_q_iron_hollow": true,
    "briefing_q_brand": true,
    "identity_greywake_briefing_class_fighter_map": true,
    "greywake_preparation_done": true,
    "early_companion_recruited": "Rhogar Valeguard",
    "blackwake_greywake_rumor": true,
    "blackwake_started": true,
    "blackwake_return_destination": "undecided",
    "act1_town_fear": 2,
    "act1_ashen_strength": 3,
    "act1_survivors_saved": 0,
    "blackwake_tollhouse_investigated": true
  },
  "clues": [
    "A stolen dispatch confirms the attacks around Iron Hollow are organized enough to rattle Greywake's quartermasters.",
    "Mira marks the switchback, likely scout perches, and the rough spacing the gang prefers when collapsing on a wagon.",
    "Dockside rumors say the Ashen Brand sells stolen ore through quiet middlemen.",
    "A Greywake drover says forged river-cut inspections are bleeding southbound caravans before they ever reach the Emberway."
  ],
  "journal": [
    "Your soldier's opening leaves you with a live look at how hard Greywake is leaning on thin patrol lines and tired veterans to protect the road south.",
    "Word reaches you that Mira Thann is quietly gathering capable hands in Greywake against a new bandit threat around Iron Hollow.",
    "Reward from South Barracks Breakout: 50 XP, 8 gp.",
    "Looted Potion of Healing x1 from South Barracks Breakout.",
    "Looted Roadworn Shortsword x1 from South Barracks Breakout.",
    "Reward from holding the barracks line: 15 XP, 6 gp.",
    "Clue: A stolen dispatch confirms the attacks around Iron Hollow are organized enough to rattle Greywake's quartermasters.",
    "Your soldier prologue ends with the trail leading toward Mira Thann's private briefing in Greywake.",
    "Clue: Mira marks the switchback, likely scout perches, and the rough spacing the gang prefers when collapsing on a wagon.",
    "Reward from Fighter identity choice: 10 XP.",
    "You treated the contract like a fighter's field briefing and forced it into useful shape.",
    "Clue: Dockside rumors say the Ashen Brand sells stolen ore through quiet middlemen.",
    "Reward from working the rumor mill: 15 XP, 12 gp.",
    "Rhogar Valeguard joined the active party.",
    "Mira Thann sent you south with a writ for Iron Hollow's steward.",
    "Clue: A Greywake drover says forged river-cut inspections are bleeding southbound caravans before they ever reach the Emberway.",
    "Quest accepted: Embers Before the Road.",
    "You turned off toward Blackwake Crossing to trace smoke, forged toll seals, and missing caravans.",
    "Reward from Charred Tollhouse Breakout: 110 XP, 16 gp.",
    "Looted Frontier Ale x1 from Charred Tollhouse Breakout.",
    "Looted Roadworn Leather Armor x1 from Charred Tollhouse Breakout.",
    "Reward from stabilizing the Blackwake tollhouse: 15 XP, 6 gp."
  ],
  "quests": {
    "trace_blackwake_cell": {
      "quest_id": "trace_blackwake_cell",
      "status": "active",
      "notes": [
        "The road to Iron Hollow can wait long enough to answer one ugly question: why are caravans vanishing before they even reach the wider Emberway?",
        "Smoke outside Greywake points toward Blackwake Crossing before the wider Emberway opens."
      ]
    }
  },
  "completed_acts": [],
  "xp": 215,
  "gold": 68,
  "inventory": {
    "C0011": 4,
    "S0002": 4,
    "S0021": 4,
    "S0005": 3,
    "S0007": 2,
    "S0006": 3,
    "S0016": 2,
    "C0000": 1,
    "E0004": 2,
    "E0097": 2,
    "E0060": 2,
    "E0112": 1,
    "E0009": 1
  },
  "short_rests_remaining": 2
}
